{
   "cursorStyle":"block",
   "cursorBlink":true,
   "fontFamily":"courier-new, courier, monospace",
   "fontSize":"15",
   "scrollback":"4000",
   "bellStyle":"both",
   "vibrancy":"",
   "lineHeight":1.0,
   "tabStopWidth":8,
   "windowBackground":"#000000",
   "tabColor":"#ffffff",
   "tabBorderColor":"#ffffff",
   "shellArgs":"--login",
   "bellSound":"https://raw.githubusercontent.com/chromium/hterm/master/audio/bell.ogg",
   "bellStyle":"both",
   "letterSpacing": 0,
   "copyOnSelect": true,
   "theme":{
     "selection": "rgba(255, 255, 255, 0.3)",
     "foreground": "#FFFFFF",
     "background": "#000000",
     "black": "#000000",
     "red": "#ff5c57",
     "brightRed": "#ff5c57",
     "green": "#5af78e",
     "brightGreen": "#5af78e",
     "yellow": "#f3f99d",
     "brightYellow": "#f3f99d",
     "magenta": "#ff6ac1",
     "brightMagenta": "#ff6ac1",
     "cyan": "#5fcbd8",
     "brightCyan": "#5fcbd8",
     "blue": "#57c7ff",
     "brightBlue": "#57c7ff",
     "white": "#ffffff",
     "brightWhite": "#FFFFFF",
     "brightBlack": "#808080",
     "cursorAccent": "#000000",
     "cursor": "#FFFFFF"
   },
   "keybindings": {
     "linux": {
       "1": { "accelerator": "ctrl+left", "command": [27, 98] },
       "2": { "accelerator": "ctrl+right", "command": [27, 102] },
       "3": { "accelerator": "home", "command": [27, 79, 72] },
       "4": { "accelerator": "end", "command": [27, 79, 70] },
       "5": { "accelerator": "ctrl+backspace", "command": [27, 127] },
       "6": { "accelerator": "ctrl+del", "command": [27, 100] },
       "7": { "accelerator": "ctrl+home", "command": [27, 119] },
       "8": { "accelerator": "ctrl+end", "command": [16, 66] }
     },
     "win32": {
       "1": { "accelerator": "ctrl+left", "command": [27, 98] },
       "2": { "accelerator":"ctrl+right", "command": [27, 102] },
       "3": { "accelerator": "home", "command": [27, 79, 72] },
       "4": { "accelerator": "end", "command": [27, 79, 70] },
       "5": { "accelerator": "ctrl+backspace", "command": [27, 127] },
       "6": { "accelerator": "cltr+del", "command": [27, 100] },
       "7": { "accelerator": "ctrl+home", "command": [27, 119] },
       "8": { "accelerator": "ctrl+end", "command": [16, 66] }
     },
     "darwin": {
       "1": { "accelerator": "alt+left", "command": [27, 98] },
       "2": { "accelerator": "alt+right", "command": [27, 102] },
       "3": { "accelerator": "command+left", "command": [27, 79, 72] },
       "4": { "accelerator": "command+right", "command": [27, 79, 70] },
       "5": { "accelerator": "alt+backspace", "command": [27, 127] },
       "6": { "accelerator": "alt+delete", "command": [27, 100] },
       "7": { "accelerator": "command+backspace", "command": [27, 119] },
       "8": { "accelerator": "command+delete", "command": [16, 66] }
     }
   }
}
